GreenPonik_WaterPump_Driver/WaterPumpDriver.py
GreenPonik_WaterPump_Driver/__init__.py
GreenPonik_WaterPump_Driver/crc8.py
GreenPonik_WaterPump_Driver/packer.py
GreenPonik_WaterPump_Driver/unpacker.py
tests/__init__.py
tests/test_Crc8.py
tests/test_Packer.py
tests/test_Unpacker.py
tests/test_WaterPumpDriver.py
greenponik_waterpump_driver-0.0.17.dist-info/METADATA
greenponik_waterpump_driver-0.0.17.dist-info/WHEEL
greenponik_waterpump_driver-0.0.17.dist-info/top_level.txt
greenponik_waterpump_driver-0.0.17.dist-info/RECORD
