Metadata-Version: 2.1
Name: greenponik-waterpump-driver
Version: 0.0.17
Summary: GreenPonik WaterPump i2c driver
Home-page: https://github.com/GreenPonik/GreenPonik_WaterPump_Driver
Author: GreenPonik SAS
Author-email: contact@greenponik.com
License: MIT
Project-URL: Source, https://github.com/GreenPonik/GreenPonik_WaterPump_Driver/
Project-URL: Bug Reports, https://github.com/GreenPonik/        GreenPonik_WaterPump_Driver/issues
Keywords: GreenPonik hydroponics WaterPump i2c driver          python hardware diy iot
Platform: UNKNOWN
Classifier: Programming Language :: Python :: 3
Classifier: License :: OSI Approved :: MIT License
Classifier: Operating System :: OS Independent
Requires-Python: >=3.6.0
Requires-Dist: adafruit-blinka
Requires-Dist: adafruit-extended-bus
